[
    {
        "id": 1001,
        "email": "user1@gmail.com",
        "name": "User 1",
        "number": "6047778888"
    },
    {
        "id": 1002,
        "email": "user2@gmail.com",
        "name": "User 2",
        "number": "6047775555"
    },
    {
        "id": 1003,
        "email": "user3@gmail.com",
        "name": "User 3",
        "number": "6047773333"
    },
    {
        "id": 1004,
        "email": "franciscoigor@gmail.com",
        "name": "Francisco Igor",
        "number": "6047723333"
    },
    {
        "id": 1005,
        "email": "another@gmail.com",
        "name": "Another User",
        "number": "6047723323"
    }
]
